[
  {
    "id": 1,
    "nombre": "Maletín de Herramientas Premium",
    "precio": 160,
    "imagenes": [
      "img/taladro-108-1.jpg",
      "img/taladro-108-2.jpg",
      "img/taladro-108-3.jpg",
      "img/taladro-108-4.jpg"
    ],
    "stock": true,
    "categoria": "herramientas",
    "descripcion": "Kit completo de dados y llaves de alta resistencia."
  },
  {
    "id": 2,
    "nombre": "Mouse Monster Gamer Led",
    "precio": 10,
    "imagenes": [
      "img/mouse-rgb-1.jpg",
      "img/mouse-rgb-2.jpg",
      "img/mouse-rgb-3.jpg",
      "img/mouse-rgb-4.jpg",
      "img/mouse-rgb-5.jpg",
      "img/mouse-rgb-6.jpg",
      "img/mouse-rgb-7.jpg"
    ],
    "stock": true,
    "categoria": "tecnologia",
    "descripcion": "Mouse ergonómico con sensor óptico regulable."
  }
]